tutil/__init__.py
tutil/dateutil.py
tutil/functional.py
tutil-0.0.6.dist-info/LICENSE
tutil-0.0.6.dist-info/METADATA
tutil-0.0.6.dist-info/WHEEL
tutil-0.0.6.dist-info/top_level.txt
tutil-0.0.6.dist-info/RECORD
